aioldata/__init__.py
aioldata/auth.py
aioldata/connector.py
aioldata/const.py
aioldata/errors.py
aioldata/parser.py
aioldata-0.0.1.dist-info/METADATA
aioldata-0.0.1.dist-info/WHEEL
aioldata-0.0.1.dist-info/licenses/LICENSE.txt
aioldata-0.0.1.dist-info/RECORD
