Metadata-Version: 2.4
Name: aioldata
Version: 0.0.1
Summary: Talk to the Leviton LDATA API asynchronously
Project-URL: Repository, https://github.com/Expl0dingBanana/aioldata
Project-URL: Changelog, https://github.com/Expl0dingBanana/aioldata/CHANGELOG.md
Author-email: Chris Dohmen <chris.dohmen11@gmail.com>
Maintainer-email: Chris Dohmen <chris.dohmen11@gmail.com>
License: The MIT License (MIT)
License-File: LICENSE.txt
Keywords: ldata,leviton
Classifier: Development Status :: 4 - Beta
Classifier: Programming Language :: Python
Classifier: Programming Language :: Python :: 3.12
Classifier: Programming Language :: Python :: 3.13
Requires-Python: >=3.12
Requires-Dist: aiohttp
Requires-Dist: securelogging>=1.0.1
Provides-Extra: test
Requires-Dist: aioresponses; extra == 'test'
Requires-Dist: anyio; extra == 'test'
Requires-Dist: pytest; extra == 'test'
Requires-Dist: pytest-aioresponses; extra == 'test'
Requires-Dist: pytest-asyncio; extra == 'test'
Requires-Dist: pytest-cov; extra == 'test'
Requires-Dist: pytest-mock; extra == 'test'
Requires-Dist: tox; extra == 'test'
